{
  "admin": [],
  "user": [
    {
      "Username": "mosin",
      "Name": "mosin mulla",
      "Mobile": "5362525235",
      "Password": "mosin7",
      "Email": "mosinmulla553@gmail.com",
      "Gender": "male",
      "id": 1
    },
    {
      "Username": "salman",
      "Name": "salman mulla",
      "Mobile": "8458586665",
      "Password": "salman123",
      "Email": "mosinmulla553@gmail.com",
      "Gender": "male",
      "id": 2
    },
    {
      "Username": "salman",
      "Name": "salman mulla",
      "Mobile": "7894561235",
      "Pan": "MKJJS1234M",
      "Password": "mOSIN@723",
      "Email": "mosinmulla553@gmail.com",
      "Gender": "male",
      "id": 3
    }
  ],
  "owner": [
    {
      "Username": "mosin ",
      "Name": "mosin mula",
      "Mobile": "7581582554",
      "Pan": "ABMAS2345M",
      "Password": "Mosin@123",
      "Email": "mosinmulla553@gmail.com",
      "Gender": "male",
      "id": 1
    },
    {
      "Username": "salman",
      "Name": "salman mulla",
      "Mobile": "7581582555",
      "Pan": "ABMAS2345M",
      "Password": "Salman@123",
      "Email": "mosinmulla553@gmail.com",
      "Gender": "male",
      "id": 2
    },
    {
      "Username": "mosin",
      "Name": "mosin mulla",
      "Mobile": "4252868692",
      "Pan": "ASDFG1234S",
      "Password": "mOSIN123@",
      "Email": "mosin34@.gamil.com",
      "Gender": "male",
      "id": 3
    },
    {
      "Username": "sahil",
      "Name": "sahil mulla",
      "Mobile": "1547862594",
      "Pan": "asder1225s",
      "Password": "Sahil@123",
      "Email": "sahil23@.gmail.com",
      "Gender": "male",
      "id": 4
    },
    {
      "Username": "tanveer",
      "Name": "tanveer mulla",
      "Mobile": "8956856655",
      "Pan": "nhjhm1234n",
      "Password": "Tanveer@123",
      "Email": "tanveer@.gmail.com",
      "Gender": "male",
      "id": 5
    },
    {
      "Username": "maaj",
      "Name": "maaj korbu",
      "Mobile": "7859585885",
      "Pan": "asedf5585m",
      "Password": "Maaj@123",
      "Email": "maaj123@gmail.com",
      "Gender": "male",
      "id": 6
    },
    {
      "Username": "aslam",
      "Name": "aslam ichalkharji",
      "Mobile": "8965959558",
      "Pan": "asedd4252s",
      "Password": "Aslam@123",
      "Email": "aslam553@gmail.com",
      "Gender": "male",
      "id": 7
    },
    {
      "Username": "Irfan",
      "Name": "irfan korbu",
      "Mobile": "7855858564",
      "Pan": "asdws4563a",
      "Password": "mosin123",
      "Email": "mosinmulla553@gmail.com",
      "Gender": "male",
      "id": 9
    }
  ],
  "hotel": [
    {
      "OwnerName": "tanvir",
      "OwnerMobNo": "785965865",
      "HotelName": "Five Star Hotel",
      "HotelAddress": "pune",
      "HotelMobile": "785656",
      "HotelMenu": "veg",
      "RoomAvailable": "80",
      "Image": "/assets/image/hotel-5.jpg",
      "id": 1
    },
    {
      "OwnerName": "mosin",
      "OwnerMobNo": "987458697458",
      "HotelName": "taj hotel",
      "HotelAddress": "umadi",
      "HotelMobile": "585874855",
      "HotelMenu": "veg",
      "RoomAvailable": "58",
      "Image": "/assets/image/hotel-3.jpg",
      "id": 2
    },
    {
      "OwnerName": "salman",
      "OwnerMobNo": "7896541236",
      "HotelName": "hotel  five star",
      "HotelAddress": "Mina Rood  ,Minar Hotel, mumbai",
      "HotelMobile": "08888696921",
      "HotelMenu": "veg",
      "RoomAvailable": "52",
      "Image": "/assets/image/hotel-4.jpg",
      "id": 3
    },
    {
      "OwnerName": "salman",
      "OwnerMobNo": "8754269852",
      "HotelName": "Uadpi Hotel",
      "HotelAddress": "Bijapur",
      "HotelMobile": "8574955545",
      "HotelMenu": "non veg",
      "RoomAvailable": "60",
      "Image": "/assets/image/hotel-10.jpg",
      "id": 5
    },
    {
      "OwnerName": "mosin",
      "OwnerMobNo": "7898548574",
      "HotelName": "sahi Hotel",
      "HotelAddress": "umadi",
      "HotelMobile": "08888696921",
      "HotelMenu": "veg",
      "RoomAvailable": "50",
      "Image": "/assets/image/hotel-8.jpg",
      "id": 6
    },
    {
      "OwnerName": "tanvir",
      "OwnerMobNo": "785965865",
      "HotelName": "Five Star Hotel",
      "HotelAddress": "pune",
      "HotelMobile": "785656",
      "HotelMenu": "veg",
      "RoomAvailable": "80",
      "Image": "/assets/image/hotel-5.jpg",
      "id": 4
    },
    {
      "OwnerName": "salman",
      "OwnerMobNo": "7896541236",
      "HotelName": "hotel  five star",
      "HotelAddress": "Mina Rood  ,Minar Hotel, mumbai",
      "HotelMobile": "08888696921",
      "HotelMenu": "veg",
      "RoomAvailable": "52",
      "Image": "/assets/image/hotel-4.jpg",
      "id": 8
    },
    {
      "OwnerName": "salman",
      "OwnerMobNo": "8754269852",
      "HotelName": "Uadpi Hotel",
      "HotelAddress": "Bijapur",
      "HotelMobile": "8574955545",
      "HotelMenu": "non veg",
      "RoomAvailable": "60",
      "Image": "/assets/image/hotel-10.jpg",
      "id": 9
    },
    {
      "OwnerName": "mosin",
      "OwnerMobNo": "7898548574",
      "HotelName": "sahi Hotel",
      "HotelAddress": "umadi",
      "HotelMobile": "08888696921",
      "HotelMenu": "veg",
      "RoomAvailable": "50",
      "Image": "/assets/image/hotel-8.jpg",
      "id": 10
    },
    {
      "OwnerName": "tanvir",
      "OwnerMobNo": "785965865",
      "HotelName": "Five Star Hotel",
      "HotelAddress": "pune",
      "HotelMobile": "785656",
      "HotelMenu": "veg",
      "RoomAvailable": "80",
      "Image": "/assets/image/hotel-5.jpg",
      "id": 11
    },
    {
      "OwnerName": "mosin",
      "OwnerMobNo": "987458697458",
      "HotelName": "taj hotel",
      "HotelAddress": "umadi",
      "HotelMobile": "585874855",
      "HotelMenu": "veg",
      "RoomAvailable": "58",
      "Image": "/assets/image/hotel-3.jpg",
      "id": 12
    },
    {
      "OwnerName": "salman",
      "OwnerMobNo": "7896541236",
      "HotelName": "hotel  five star",
      "HotelAddress": "Mina Rood  ,Minar Hotel, mumbai",
      "HotelMobile": "08888696921",
      "HotelMenu": "veg",
      "RoomAvailable": "52",
      "Image": "/assets/image/hotel-4.jpg",
      "id": 13
    },
    {
      "OwnerName": "salman",
      "OwnerMobNo": "8754269852",
      "HotelName": "Uadpi Hotel",
      "HotelAddress": "Bijapur",
      "HotelMobile": "8574955545",
      "HotelMenu": "non veg",
      "RoomAvailable": "60",
      "Image": "/assets/image/hotel-10.jpg",
      "id": 15
    },
    {
      "OwnerName": "mosin",
      "OwnerMobNo": "7898548574",
      "HotelName": "sahi Hotel",
      "HotelAddress": "umadi",
      "HotelMobile": "08888696921",
      "HotelMenu": "veg",
      "RoomAvailable": "50",
      "Image": "/assets/image/hotel-8.jpg",
      "id": 16
    },
    {
      "OwnerName": "tanvir",
      "OwnerMobNo": "785965865",
      "HotelName": "Five Star Hotel",
      "HotelAddress": "pune",
      "HotelMobile": "785656",
      "HotelMenu": "veg",
      "RoomAvailable": "80",
      "Image": "/assets/image/hotel-5.jpg",
      "id": 14
    },
    {
      "OwnerName": "mosin",
      "OwnerMobNo": "987458697458",
      "HotelName": "taj hotel",
      "HotelAddress": "umadi",
      "HotelMobile": "585874855",
      "HotelMenu": "veg",
      "RoomAvailable": "58",
      "Image": "/assets/image/hotel-3.jpg",
      "id": 17
    },
    {
      "OwnerName": "salman",
      "OwnerMobNo": "7896541236",
      "HotelName": "hotel  five star",
      "HotelAddress": "Mina Rood  ,Minar Hotel, mumbai",
      "HotelMobile": "08888696921",
      "HotelMenu": "veg",
      "RoomAvailable": "52",
      "Image": "/assets/image/hotel-4.jpg",
      "id": 18
    },
    {
      "OwnerName": "salman",
      "OwnerMobNo": "8754269852",
      "HotelName": "Uadpi Hotel",
      "HotelAddress": "Bijapur",
      "HotelMobile": "8574955545",
      "HotelMenu": "non veg",
      "RoomAvailable": "60",
      "Image": "/assets/image/hotel-10.jpg",
      "id": 19
    },
    {
      "OwnerName": "mosin",
      "OwnerMobNo": "7898548574",
      "HotelName": "sahi Hotel",
      "HotelAddress": "umadi",
      "HotelMobile": "08888696921",
      "HotelMenu": "veg",
      "RoomAvailable": "50",
      "Image": "/assets/image/hotel-8.jpg",
      "id": 20
    },
    {
      "OwnerName": "mosin",
      "OwnerMobNo": "7898548574",
      "HotelName": "sahi Hotel",
      "HotelAddress": "umadi",
      "HotelMobile": "08888696921",
      "HotelMenu": "NONveg",
      "RoomAvailable": "500",
      "Image": "/assets/image/hotel-8.jpg",
      "id": 21
    },
    {
      "OwnerName": "mosin",
      "OwnerMobNo": "7898548574",
      "HotelName": "sahi Hotel",
      "HotelAddress": "umadi",
      "HotelMobile": "08888696921",
      "HotelMenu": "NONveg",
      "RoomAvailable": "500",
      "Image": "/assets/image/hotel-8.jpg",
      "id": 22
    },
    {
      "OwnerName": "mosin",
      "OwnerMobNo": "7898548574",
      "HotelName": "sahi Hotel",
      "HotelAddress": "umadi",
      "HotelMobile": "08888696921",
      "HotelMenu": "veg",
      "RoomAvailable": "50",
      "Image": "/assets/image/hotel-8.jpg",
      "id": 23
    }
  ],
  "hotels": [
    {
      "name": "Green Valey",
      "ownerName": "mosin",
      "phone": 8888696921,
      "email": "Green@gmail.com",
      "menu": "Manchurian",
      "discription": "The Best manchurian in the world",
      "address": "Nehru Chauk , Amaravati - 421212",
      "arooms": 300,
      "id": 1
    },
    {
      "name": "Five Star Hotel",
      "ownerName": "mosin",
      "phone": 8888981212,
      "email": "star@gmail.com",
      "menu": "Coffee",
      "discription": "The Best Coffee you will ever have !!",
      "address": "Chatrapati Shivaji Nagar, Pune - 431213",
      "arooms": 25,
      "id": 2
    },
    {
      "name": "Hotel Lotus",
      "ownerName": "mosin",
      "phone": 7499269640,
      "email": "Tanaya@gmail.com",
      "menu": "Chat",
      "discription": "The best Chat in the whole universe !!",
      "address": "pundalik baba nagar, \nAmaravati - 444604",
      "arooms": 200,
      "id": 3
    },
    {
      "name": "Taj Hotel",
      "ownerName": "mosin",
      "phone": 9421322354,
      "email": "Taj@gmail.com",
      "menu": "Dal Tadka",
      "discription": "The greatest hotel of all time",
      "address": "Chatrapti sambhaji maharaj - 431213",
      "arooms": 300,
      "id": 4
    },
    {
      "name": "Green Valey",
      "ownerName": "mosin",
      "phone": 8888696921,
      "email": "Green@gmail.com",
      "menu": "Manchurian",
      "discription": "The Best manchurian in the world",
      "address": "Nehru Chauk , Amaravati - 421212",
      "arooms": 300,
      "id": 1
    },
    {
      "name": "Minar Hotel",
      "ownerName": "mosin",
      "phone": "8549895",
      "email": "minarhotel@gmail.com",
      "menu": "non veag",
      "discription": "use full hotel",
      "address": "Mina Rood  ,Minar Hotel, mumbai",
      "arooms": 101,
      "id": 6
    },
    {
      "name": "dassf",
      "ownerName": "mosin",
      "phone": "8549895",
      "email": "mosinmulla553@gmail",
      "menu": "dFFFCD",
      "discription": "dfF",
      "address": "Mina Rood  ,Minar Hotel, mumbai",
      "arooms": "20",
      "id": 7
    }
  ]
}